sardynka_py/__init__.py
sardynka_py/hello.py
sardynka_py-0.0.1.dist-info/LICENSE
sardynka_py-0.0.1.dist-info/METADATA
sardynka_py-0.0.1.dist-info/WHEEL
sardynka_py-0.0.1.dist-info/top_level.txt
sardynka_py-0.0.1.dist-info/RECORD
