Metadata-Version: 2.1
Name: sardynka-py
Version: 0.0.1
Summary: cryptography wrapper
Home-page: UNKNOWN
Author: pawlaczyk (Dominika Pawlaczyk)
Author-email: dominika.pawlaczyk9@gmail.com
License: UNKNOWN
Keywords: python,AES,ECC,cryptography
Platform: UNKNOWN
Classifier: Development Status :: 1 - Planning
Classifier: Intended Audience :: Developers
Classifier: Programming Language :: Python :: 3
Classifier: Operating System :: Unix
Classifier: Operating System :: MacOS :: MacOS X
Classifier: Operating System :: Microsoft :: Windows
License-File: LICENSE
Requires-Dist: pycryptodome
